LICENSE
README.md
setup.py
binlogs/__init__.py
binlogs/append.py
binlogs/server.py
binlogs/tail.py
binlogs.egg-info/PKG-INFO
binlogs.egg-info/SOURCES.txt
binlogs.egg-info/dependency_links.txt
binlogs.egg-info/top_level.txt